ELO_utils-1.3.1.dist-info/DESCRIPTION.rst
ELO_utils-1.3.1.dist-info/METADATA
ELO_utils-1.3.1.dist-info/RECORD
ELO_utils-1.3.1.dist-info/WHEEL
ELO_utils-1.3.1.dist-info/metadata.json
ELO_utils-1.3.1.dist-info/top_level.txt
ELOutils/ELO.py
ELOutils/__init__.py
