Metadata-Version: 2.0
Name: ELO-utils
Version: 1.3.1
Summary: ELO calculations for python
Home-page: https://github.com/danybeam/ELO_Utils
Author: danybeam
Author-email: danybeam@gmail.com
License: MIT
Platform: UNKNOWN
Classifier: License :: OSI Approved :: MIT License
Classifier: Programming Language :: Python
Classifier: Programming Language :: Python :: 3
Classifier: Programming Language :: Python :: 3.7
Classifier: Operating System :: OS Independent
Requires-Python: >=3.7.0
